catabra_lib/__init__.py
catabra_lib/__version__.py
catabra_lib/bootstrapping.py
catabra_lib/metrics.py
catabra_lib/plotting/__init__.py
catabra_lib/plotting/_common.py
catabra_lib/plotting/_matplotlib.py
catabra_lib/plotting/_plotly.py
catabra_lib/plotting/red_blue.pkl
catabra_lib/preprocessing.py
catabra_lib/split.py
catabra_lib/statistics.py
catabra_lib/util.py
catabra_lib-0.0.3.dist-info/LICENSE
catabra_lib-0.0.3.dist-info/METADATA
catabra_lib-0.0.3.dist-info/WHEEL
catabra_lib-0.0.3.dist-info/RECORD
