Metadata-Version: 2.1
Name: catabra-lib
Version: 0.0.3
Summary: CaTabRa-lib is a library with useful data-science-related functions and classes built atop scikit-learn
Home-page: https://github.com/risc-mi/catabra-lib
License: Apache 2.0 with Commons Clause
Author: RISC Software GmbH
Requires-Python: >=3.6.1,<4.0.0
Classifier: License :: Other/Proprietary License
Classifier: Programming Language :: Python :: 3
Classifier: Programming Language :: Python :: 3.7
Classifier: Programming Language :: Python :: 3.8
Classifier: Programming Language :: Python :: 3.9
Classifier: Programming Language :: Python :: 3.10
Classifier: Programming Language :: Python :: 3.11
Classifier: Programming Language :: Python :: 3.12
Requires-Dist: scikit-learn (>=0.23.0) ; python_version < "3.9"
Requires-Dist: scikit-learn (>=0.24.0) ; python_version >= "3.9"
Project-URL: Repository, https://github.com/risc-mi/catabra-lib
